setup.py
django_dress_blog.egg-info/PKG-INFO
django_dress_blog.egg-info/SOURCES.txt
django_dress_blog.egg-info/dependency_links.txt
django_dress_blog.egg-info/top_level.txt
dress_blog/__init__.py
dress_blog/admin.py
dress_blog/context_processors.py
dress_blog/diary_urls.py
dress_blog/feeds.py
dress_blog/models.py
dress_blog/quote_urls.py
dress_blog/search_indexes.py
dress_blog/sitemaps.py
dress_blog/story_urls.py
dress_blog/urls.py
dress_blog/utils.py
dress_blog/views.py
dress_blog/templatetags/__init__.py
dress_blog/templatetags/archive.py
dress_blog/templatetags/colloquial_date.py
dress_blog/templatetags/diary.py
dress_blog/templatetags/quotes.py
dress_blog/templatetags/stories.py