Metadata-Version: 1.0
Name: django-dress-blog
Version: 0.1a
Summary: Django blogging app with stories, quotes, diary, comments and tags.
Home-page: http://pypi.python.org/pypi/django-dress-blog/
Author: Daniel Rus Morales
Author-email: inbox@danir.us
License: MIT
Platform: UNKNOWN
Classifier: Development Status :: 4 - Beta
Classifier: Environment :: Web Environment
Classifier: Intended Audience :: Developers
Classifier: License :: OSI Approved :: MIT License
Classifier: Operating System :: OS Independent
Classifier: Programming Language :: Python
Classifier: Framework :: Django
